{"nodes": [{"id": "frontend_src_components_sandboxterminal_tsx", "label": "SandboxTerminal.tsx", "file_type": "code", "source_file": "frontend/src/components/SandboxTerminal.tsx", "source_location": "L1"}, {"id": "sandboxterminal_createline", "label": "createLine()", "file_type": "code", "source_file": "frontend/src/components/SandboxTerminal.tsx", "source_location": "L17"}, {"id": "sandboxterminal_startrunning", "label": "startRunning()", "file_type": "code", "source_file": "frontend/src/components/SandboxTerminal.tsx", "source_location": "L44"}, {"id": "sandboxterminal_stoprunning", "label": "stopRunning()", "file_type": "code", "source_file": "frontend/src/components/SandboxTerminal.tsx", "source_location": "L51"}, {"id": "sandboxterminal_startsyntheticscanstream", "label": "startSyntheticScanStream()", "file_type": "code", "source_file": "frontend/src/components/SandboxTerminal.tsx", "source_location": "L62"}, {"id": "sandboxterminal_executecommand", "label": "executeCommand()", "file_type": "code", "source_file": "frontend/src/components/SandboxTerminal.tsx", "source_location": "L115"}, {"id": "sandboxterminal_handlesubmit", "label": "handleSubmit()", "file_type": "code", "source_file": "frontend/src/components/SandboxTerminal.tsx", "source_location": "L231"}], "edges": [{"source": "frontend_src_components_sandboxterminal_tsx", "target": "react", "relation": "imports_from", "confidence": "EXTRACTED", "source_file": "frontend/src/components/SandboxTerminal.tsx", "source_location": "L1", "weight": 1.0}, {"source": "frontend_src_components_sandboxterminal_tsx", "target": "frontend_src_services_api", "relation": "imports_from", "confidence": "EXTRACTED", "source_file": "frontend/src/components/SandboxTerminal.tsx", "source_location": "L2", "weight": 1.0}, {"source": "frontend_src_components_sandboxterminal_tsx", "target": "sandboxterminal_createline", "relation": "contains", "confidence": "EXTRACTED", "source_file": "frontend/src/components/SandboxTerminal.tsx", "source_location": "L17", "weight": 1.0}, {"source": "frontend_src_components_sandboxterminal_tsx", "target": "sandboxterminal_startrunning", "relation": "contains", "confidence": "EXTRACTED", "source_file": "frontend/src/components/SandboxTerminal.tsx", "source_location": "L44", "weight": 1.0}, {"source": "frontend_src_components_sandboxterminal_tsx", "target": "sandboxterminal_stoprunning", "relation": "contains", "confidence": "EXTRACTED", "source_file": "frontend/src/components/SandboxTerminal.tsx", "source_location": "L51", "weight": 1.0}, {"source": "frontend_src_components_sandboxterminal_tsx", "target": "sandboxterminal_startsyntheticscanstream", "relation": "contains", "confidence": "EXTRACTED", "source_file": "frontend/src/components/SandboxTerminal.tsx", "source_location": "L62", "weight": 1.0}, {"source": "frontend_src_components_sandboxterminal_tsx", "target": "sandboxterminal_executecommand", "relation": "contains", "confidence": "EXTRACTED", "source_file": "frontend/src/components/SandboxTerminal.tsx", "source_location": "L115", "weight": 1.0}, {"source": "frontend_src_components_sandboxterminal_tsx", "target": "sandboxterminal_handlesubmit", "relation": "contains", "confidence": "EXTRACTED", "source_file": "frontend/src/components/SandboxTerminal.tsx", "source_location": "L231", "weight": 1.0}, {"source": "sandboxterminal_executecommand", "target": "sandboxterminal_startrunning", "relation": "calls", "confidence": "EXTRACTED", "source_file": "frontend/src/components/SandboxTerminal.tsx", "source_location": "L154", "weight": 1.0}, {"source": "sandboxterminal_executecommand", "target": "sandboxterminal_startsyntheticscanstream", "relation": "calls", "confidence": "EXTRACTED", "source_file": "frontend/src/components/SandboxTerminal.tsx", "source_location": "L155", "weight": 1.0}, {"source": "sandboxterminal_executecommand", "target": "sandboxterminal_stoprunning", "relation": "calls", "confidence": "EXTRACTED", "source_file": "frontend/src/components/SandboxTerminal.tsx", "source_location": "L171", "weight": 1.0}, {"source": "sandboxterminal_handlesubmit", "target": "sandboxterminal_executecommand", "relation": "calls", "confidence": "EXTRACTED", "source_file": "frontend/src/components/SandboxTerminal.tsx", "source_location": "L235", "weight": 1.0}], "raw_calls": [{"caller_nid": "sandboxterminal_createline", "callee": "now", "source_file": "frontend/src/components/SandboxTerminal.tsx", "source_location": "L19"}, {"caller_nid": "sandboxterminal_createline", "callee": "slice", "source_file": "frontend/src/components/SandboxTerminal.tsx", "source_location": "L19"}, {"caller_nid": "sandboxterminal_createline", "callee": "toString", "source_file": "frontend/src/components/SandboxTerminal.tsx", "source_location": "L19"}, {"caller_nid": "sandboxterminal_createline", "callee": "random", "source_file": "frontend/src/components/SandboxTerminal.tsx", "source_location": "L19"}, {"caller_nid": "sandboxterminal_startrunning", "callee": "setRunning", "source_file": "frontend/src/components/SandboxTerminal.tsx", "source_location": "L47"}, {"caller_nid": "sandboxterminal_stoprunning", "callee": "setRunning", "source_file": "frontend/src/components/SandboxTerminal.tsx", "source_location": "L53"}, {"caller_nid": "sandboxterminal_stoprunning", "callee": "setPhaseLabel", "source_file": "frontend/src/components/SandboxTerminal.tsx", "source_location": "L54"}, {"caller_nid": "sandboxterminal_stoprunning", "callee": "setPhaseProgress", "source_file": "frontend/src/components/SandboxTerminal.tsx", "source_location": "L55"}, {"caller_nid": "sandboxterminal_stoprunning", "callee": "clearInterval", "source_file": "frontend/src/components/SandboxTerminal.tsx", "source_location": "L57"}, {"caller_nid": "sandboxterminal_startsyntheticscanstream", "callee": "replace", "source_file": "frontend/src/components/SandboxTerminal.tsx", "source_location": "L75"}, {"caller_nid": "sandboxterminal_startsyntheticscanstream", "callee": "slice", "source_file": "frontend/src/components/SandboxTerminal.tsx", "source_location": "L75"}, {"caller_nid": "sandboxterminal_startsyntheticscanstream", "callee": "filter", "source_file": "frontend/src/components/SandboxTerminal.tsx", "source_location": "L75"}, {"caller_nid": "sandboxterminal_startsyntheticscanstream", "callee": "split", "source_file": "frontend/src/components/SandboxTerminal.tsx", "source_location": "L75"}, {"caller_nid": "sandboxterminal_startsyntheticscanstream", "callee": "setPhaseLabel", "source_file": "frontend/src/components/SandboxTerminal.tsx", "source_location": "L86"}, {"caller_nid": "sandboxterminal_startsyntheticscanstream", "callee": "setPhaseProgress", "source_file": "frontend/src/components/SandboxTerminal.tsx", "source_location": "L87"}, {"caller_nid": "sandboxterminal_startsyntheticscanstream", "callee": "setLines", "source_file": "frontend/src/components/SandboxTerminal.tsx", "source_location": "L88"}, {"caller_nid": "sandboxterminal_startsyntheticscanstream", "callee": "setInterval", "source_file": "frontend/src/components/SandboxTerminal.tsx", "source_location": "L94"}, {"caller_nid": "sandboxterminal_executecommand", "callee": "trim", "source_file": "frontend/src/components/SandboxTerminal.tsx", "source_location": "L116"}, {"caller_nid": "sandboxterminal_executecommand", "callee": "setLines", "source_file": "frontend/src/components/SandboxTerminal.tsx", "source_location": "L120"}, {"caller_nid": "sandboxterminal_executecommand", "callee": "setLines", "source_file": "frontend/src/components/SandboxTerminal.tsx", "source_location": "L127"}, {"caller_nid": "sandboxterminal_executecommand", "callee": "split", "source_file": "frontend/src/components/SandboxTerminal.tsx", "source_location": "L129"}, {"caller_nid": "sandboxterminal_executecommand", "callee": "toLowerCase", "source_file": "frontend/src/components/SandboxTerminal.tsx", "source_location": "L130"}, {"caller_nid": "sandboxterminal_executecommand", "callee": "setLines", "source_file": "frontend/src/components/SandboxTerminal.tsx", "source_location": "L133"}, {"caller_nid": "sandboxterminal_executecommand", "callee": "setLines", "source_file": "frontend/src/components/SandboxTerminal.tsx", "source_location": "L138"}, {"caller_nid": "sandboxterminal_executecommand", "callee": "trim", "source_file": "frontend/src/components/SandboxTerminal.tsx", "source_location": "L146"}, {"caller_nid": "sandboxterminal_executecommand", "callee": "join", "source_file": "frontend/src/components/SandboxTerminal.tsx", "source_location": "L146"}, {"caller_nid": "sandboxterminal_executecommand", "callee": "trim", "source_file": "frontend/src/components/SandboxTerminal.tsx", "source_location": "L147"}, {"caller_nid": "sandboxterminal_executecommand", "callee": "setLines", "source_file": "frontend/src/components/SandboxTerminal.tsx", "source_location": "L148"}, {"caller_nid": "sandboxterminal_executecommand", "callee": "fetchScanTerminalLines", "source_file": "frontend/src/components/SandboxTerminal.tsx", "source_location": "L157"}, {"caller_nid": "sandboxterminal_executecommand", "callee": "setPhaseLabel", "source_file": "frontend/src/components/SandboxTerminal.tsx", "source_location": "L158"}, {"caller_nid": "sandboxterminal_executecommand", "callee": "setPhaseProgress", "source_file": "frontend/src/components/SandboxTerminal.tsx", "source_location": "L159"}, {"caller_nid": "sandboxterminal_executecommand", "callee": "setLines", "source_file": "frontend/src/components/SandboxTerminal.tsx", "source_location": "L160"}, {"caller_nid": "sandboxterminal_executecommand", "callee": "setLines", "source_file": "frontend/src/components/SandboxTerminal.tsx", "source_location": "L166"}, {"caller_nid": "sandboxterminal_executecommand", "callee": "fetchScans", "source_file": "frontend/src/components/SandboxTerminal.tsx", "source_location": "L179"}, {"caller_nid": "sandboxterminal_executecommand", "callee": "setLines", "source_file": "frontend/src/components/SandboxTerminal.tsx", "source_location": "L180"}, {"caller_nid": "sandboxterminal_executecommand", "callee": "setLines", "source_file": "frontend/src/components/SandboxTerminal.tsx", "source_location": "L185"}, {"caller_nid": "sandboxterminal_executecommand", "callee": "fetchFindings", "source_file": "frontend/src/components/SandboxTerminal.tsx", "source_location": "L198"}, {"caller_nid": "sandboxterminal_executecommand", "callee": "reduce", "source_file": "frontend/src/components/SandboxTerminal.tsx", "source_location": "L199"}, {"caller_nid": "sandboxterminal_executecommand", "callee": "setLines", "source_file": "frontend/src/components/SandboxTerminal.tsx", "source_location": "L207"}, {"caller_nid": "sandboxterminal_executecommand", "callee": "setLines", "source_file": "frontend/src/components/SandboxTerminal.tsx", "source_location": "L215"}, {"caller_nid": "sandboxterminal_executecommand", "callee": "setLines", "source_file": "frontend/src/components/SandboxTerminal.tsx", "source_location": "L225"}, {"caller_nid": "sandboxterminal_handlesubmit", "callee": "preventDefault", "source_file": "frontend/src/components/SandboxTerminal.tsx", "source_location": "L232"}, {"caller_nid": "sandboxterminal_handlesubmit", "callee": "setCommand", "source_file": "frontend/src/components/SandboxTerminal.tsx", "source_location": "L234"}]}